cadet_rdm-1.0.1.dist-info/licenses/LICENSE
cadetrdm/__init__.py
cadetrdm/batch_runner.py
cadetrdm/cli_integration.py
cadetrdm/conda_env_utils.py
cadetrdm/environment.py
cadetrdm/initialize_repo.py
cadetrdm/io_utils.py
cadetrdm/jupyter_functionality.py
cadetrdm/logging.py
cadetrdm/options.py
cadetrdm/remote_integration.py
cadetrdm/repositories.py
cadetrdm/web_utils.py
cadetrdm/wrapper.py
cadetrdm/batch_running/__init__.py
cadetrdm/batch_running/case.py
cadetrdm/batch_running/study.py
cadetrdm/container/ApptainerAdapter.py
cadetrdm/container/__init__.py
cadetrdm/container/containerAdapter.py
cadetrdm/container/dockerAdapter.py
cadetrdm/container/podmanAdapter.py
cadetrdm/templates/__init__.py
cadetrdm/templates/dockerfile_template.py
cadetrdm/tools/fix_repos.py
cadetrdm/tools/process_example.py
cadetrdm/tools/recover_options.py
cadet_rdm-1.0.1.dist-info/METADATA
cadet_rdm-1.0.1.dist-info/WHEEL
cadet_rdm-1.0.1.dist-info/entry_points.txt
cadet_rdm-1.0.1.dist-info/top_level.txt
cadet_rdm-1.0.1.dist-info/RECORD
