Metadata-Version: 2.4
Name: CADET-RDM
Version: 1.0.1
Summary: A Python toolbox for research data management.
Author-email: Ronald Jäpel <r.jaepel@fz-juelich.de>, Johannes Schmölder <j.schmoelder@fz-juelich.de>, Eric von Lieres <e.von.lieres@fz-juelich.de>, Hannah Lanzrath <h.lanzrath@fz-juelich.de>
License: GPLv3
Project-URL: homepage, https://github.com/cadet/CADET-RDM
Project-URL: documentation, https://cadet-rdm.readthedocs.io/en/latest/index.html
Project-URL: Bug Tracker, https://github.com/cadet/CADET-RDM/issues
Keywords: research data management
Classifier: Programming Language :: Python :: 3
Classifier: Operating System :: OS Independent
Classifier: License :: OSI Approved :: GNU General Public License v3 (GPLv3)
Classifier: Intended Audience :: Science/Research
Requires-Python: >=3.11
License-File: LICENSE
Requires-Dist: gitpython>=3.1
Requires-Dist: python-gitlab
Requires-Dist: pygithub
Requires-Dist: click
Requires-Dist: tabulate
Requires-Dist: keyring
Requires-Dist: addict
Requires-Dist: numpy
Requires-Dist: pyyaml
Requires-Dist: semantic-version
Requires-Dist: docker
Requires-Dist: cookiecutter
Provides-Extra: jupyter
Requires-Dist: nbformat; extra == "jupyter"
Requires-Dist: nbconvert; extra == "jupyter"
Requires-Dist: ipylab; extra == "jupyter"
Requires-Dist: junix; extra == "jupyter"
Requires-Dist: jupytext; extra == "jupyter"
Requires-Dist: jupyterlab; extra == "jupyter"
Dynamic: license-file
